{
  "version": "recommended_native_256_cases_v1",
  "standard_id": "PGDA_NATIVE_256_RELEASE_STANDARD_V1",
  "cases": [
    {
      "case_id": "N256_F01_GENTLE_DEEP_MODERATE_POS",
      "family": "native_gentle_deep_moderate",
      "target_presence": true,
      "material_set": "native_deep_moderate",
      "grid": {"dl_m": 0.0225, "trace_count": 256, "trace_spacing_m": 0.09, "solver_time_window_ns": 701.0, "pml_cells": [20, 20, 0, 20, 20, 0], "guard_cells": 20},
      "source": {"center_frequency_hz": 55000000.0, "tx_rx_offset_m": 0.18},
      "scan_left_margin_m": 110.0,
      "scan_right_margin_m": 110.0,
      "domain_min_y_m": 36.0,
      "terrain": {"kind": "control_points", "control_point_fractions": [0.0, 0.22, 0.49, 0.74, 1.0], "elevation_offsets_m": [0.0, 0.12, -0.10, 0.15, 0.03], "smoothing_length_m": 1.8},
      "flight_height_agl_m": 8.0,
      "interface": {"kind": "control_points", "base_depth_m": 15.6, "control_point_fractions": [0.0, 0.18, 0.43, 0.68, 0.86, 1.0], "depth_offsets_m": [-0.30, -0.08, 0.32, 0.58, 0.28, 0.10], "smoothing_length_m": 1.65},
      "cover_boundary": {"kind": "flat", "base_depth_m": 3.8},
      "purpose": "Primary native-width positive with a single gently varying deep basal interface."
    },
    {
      "case_id": "N256_F02_DEEP_LOW_CONTRAST_POS",
      "family": "native_deep_low_contrast",
      "target_presence": true,
      "material_set": "native_deep_low_contrast",
      "grid": {"dl_m": 0.0225, "trace_count": 256, "trace_spacing_m": 0.09, "solver_time_window_ns": 701.0, "pml_cells": [20, 20, 0, 20, 20, 0], "guard_cells": 20},
      "source": {"center_frequency_hz": 55000000.0, "tx_rx_offset_m": 0.18},
      "scan_left_margin_m": 110.0,
      "scan_right_margin_m": 110.0,
      "domain_min_y_m": 36.0,
      "terrain": {"kind": "control_points", "control_point_fractions": [0.0, 0.20, 0.47, 0.76, 1.0], "elevation_offsets_m": [0.0, -0.16, 0.10, -0.08, 0.06], "smoothing_length_m": 1.9},
      "flight_height_agl_m": 9.0,
      "interface": {"kind": "control_points", "base_depth_m": 16.35, "control_point_fractions": [0.0, 0.16, 0.37, 0.60, 0.82, 1.0], "depth_offsets_m": [-0.18, 0.10, 0.48, 0.34, 0.62, 0.22], "smoothing_length_m": 1.8},
      "cover_boundary": {"kind": "flat", "base_depth_m": 4.2},
      "purpose": "Deep low-contrast positive for detectability and calibration stress testing."
    },
    {
      "case_id": "N256_F03_THICK_WEATHERING_DROPOUT_POS",
      "family": "native_thick_weathering_dropout",
      "target_presence": true,
      "material_set": "native_deep_moderate",
      "grid": {"dl_m": 0.0225, "trace_count": 256, "trace_spacing_m": 0.09, "solver_time_window_ns": 701.0, "pml_cells": [20, 20, 0, 20, 20, 0], "guard_cells": 20},
      "source": {"center_frequency_hz": 55000000.0, "tx_rx_offset_m": 0.18},
      "scan_left_margin_m": 110.0,
      "scan_right_margin_m": 110.0,
      "domain_min_y_m": 36.0,
      "terrain": {"kind": "control_points", "control_point_fractions": [0.0, 0.27, 0.52, 0.78, 1.0], "elevation_offsets_m": [0.0, 0.07, -0.18, 0.13, -0.02], "smoothing_length_m": 2.0},
      "flight_height_agl_m": 8.0,
      "interface": {"kind": "control_points", "base_depth_m": 15.85, "control_point_fractions": [0.0, 0.14, 0.33, 0.53, 0.73, 0.90, 1.0], "depth_offsets_m": [-0.12, 0.26, 0.08, 0.62, 0.40, 0.68, 0.24], "smoothing_length_m": 1.55},
      "cover_boundary": {"kind": "flat", "base_depth_m": 5.1},
      "purpose": "Thicker weathered cover creates a physically causal weak-response challenge without disconnected target geometry."
    },
    {
      "case_id": "N256_F04_CURVED_MODERATE_POS",
      "family": "native_curved_moderate",
      "target_presence": true,
      "material_set": "native_deep_moderate",
      "grid": {"dl_m": 0.0225, "trace_count": 256, "trace_spacing_m": 0.09, "solver_time_window_ns": 701.0, "pml_cells": [20, 20, 0, 20, 20, 0], "guard_cells": 20},
      "source": {"center_frequency_hz": 55000000.0, "tx_rx_offset_m": 0.18},
      "scan_left_margin_m": 110.0,
      "scan_right_margin_m": 110.0,
      "domain_min_y_m": 36.0,
      "terrain": {"kind": "control_points", "control_point_fractions": [0.0, 0.25, 0.50, 0.75, 1.0], "elevation_offsets_m": [0.0, 0.20, -0.06, 0.16, 0.0], "smoothing_length_m": 1.7},
      "flight_height_agl_m": 7.5,
      "interface": {"kind": "control_points", "base_depth_m": 14.75, "control_point_fractions": [0.0, 0.13, 0.30, 0.49, 0.67, 0.85, 1.0], "depth_offsets_m": [-0.22, 0.10, 0.52, 0.26, 0.71, 0.18, -0.06], "smoothing_length_m": 1.35},
      "cover_boundary": {"kind": "flat", "base_depth_m": 3.5},
      "purpose": "Continuous higher-curvature positive; curvature remains smooth enough for a single geologic interface."
    },
    {
      "case_id": "N256_N01_CLEAN_BACKGROUND_NEG",
      "family": "native_clean_background_negative",
      "target_presence": false,
      "material_set": "native_deep_moderate",
      "grid": {"dl_m": 0.0225, "trace_count": 256, "trace_spacing_m": 0.09, "solver_time_window_ns": 701.0, "pml_cells": [20, 20, 0, 20, 20, 0], "guard_cells": 20},
      "source": {"center_frequency_hz": 55000000.0, "tx_rx_offset_m": 0.18},
      "scan_left_margin_m": 110.0,
      "scan_right_margin_m": 110.0,
      "domain_min_y_m": 36.0,
      "terrain": {"kind": "control_points", "control_point_fractions": [0.0, 0.24, 0.53, 0.79, 1.0], "elevation_offsets_m": [0.0, 0.10, -0.09, 0.08, 0.01], "smoothing_length_m": 1.8},
      "flight_height_agl_m": 8.0,
      "interface": {"kind": "control_points", "base_depth_m": 15.5, "control_point_fractions": [0.0, 0.30, 0.57, 0.83, 1.0], "depth_offsets_m": [0.0, 0.22, 0.36, 0.12, 0.04], "smoothing_length_m": 1.8},
      "cover_boundary": {"kind": "flat", "base_depth_m": 3.8},
      "purpose": "True target-absent background with the same upper-layer family as deep positives."
    },
    {
      "case_id": "N256_N02_SHALLOW_COHERENT_HARD_NEG",
      "family": "native_shallow_coherent_hard_negative",
      "target_presence": false,
      "material_set": "native_hard_negative_upper_reflector",
      "grid": {"dl_m": 0.0225, "trace_count": 256, "trace_spacing_m": 0.09, "solver_time_window_ns": 701.0, "pml_cells": [20, 20, 0, 20, 20, 0], "guard_cells": 20},
      "source": {"center_frequency_hz": 55000000.0, "tx_rx_offset_m": 0.18},
      "scan_left_margin_m": 110.0,
      "scan_right_margin_m": 110.0,
      "domain_min_y_m": 36.0,
      "terrain": {"kind": "control_points", "control_point_fractions": [0.0, 0.17, 0.44, 0.70, 1.0], "elevation_offsets_m": [0.0, -0.14, 0.14, -0.06, 0.03], "smoothing_length_m": 1.55},
      "flight_height_agl_m": 7.5,
      "interface": {"kind": "control_points", "base_depth_m": 14.8, "control_point_fractions": [0.0, 0.21, 0.49, 0.76, 1.0], "depth_offsets_m": [0.0, 0.18, 0.45, 0.20, 0.05], "smoothing_length_m": 1.65},
      "cover_boundary": {"kind": "flat", "base_depth_m": 2.6},
      "purpose": "Target-absent hard negative: a strong shallow cover/weathered reflector must not be mislabeled as basal."
    }
  ]
}
